PPDyn/__init__.py
PPDyn/animate.py
PPDyn/diagn.py
PPDyn/init.py
PPDyn/initial.py
PPDyn/input.ini
PPDyn/main.py
PPDyn/ppdplot.py
PPDyn/ppdyn.py
PPDyn/pusher_parallel.py
PPDyn/pusher_serial.py
PPDyn/realtime.py
PPDyn/thermostat.py
PPDyn/vtk_data.py
PPDyn-1.0.8.dist-info/LICENSE
PPDyn-1.0.8.dist-info/METADATA
PPDyn-1.0.8.dist-info/WHEEL
PPDyn-1.0.8.dist-info/top_level.txt
PPDyn-1.0.8.dist-info/RECORD
