Metadata-Version: 2.1
Name: PPDyn
Version: 1.0.8
Summary: A python package to simulate plasma particles using Molecular Dynamics Algorithm.
Home-page: https://github.com/sayanadhikari/PPDyn
Author: Sayan Adhikari
Author-email: sayanadhikari207@gmail.com
License: MIT
Project-URL: Bug Tracker, https://github.com/sayanadhikari/PPDyn/issues
Platform: UNKNOWN
Classifier: Programming Language :: Python :: 3
Classifier: License :: OSI Approved :: MIT License
Classifier: Operating System :: OS Independent
Requires-Python: >=3.6
Requires-Dist: numpy
Requires-Dist: scipy
Requires-Dist: ini-parser
Requires-Dist: numba
Requires-Dist: h5py
Requires-Dist: matplotlib
